[
    {
        "title": "10 Things I Wish I Knew When I Was a College Freshman",
        "topic": "College",
        "published date": "May 7, 2024",
        "read time": 6
    },
    {
        "title": "South Korea in the Winter",
        "topic": "Culture",
        "published date": "May 8, 2024",
        "read time": 8
    },
    {
        "title": "21 Lessons Learned From a 21 Year Old",
        "topic": "Creative Writing",
        "published date": "May 9, 2024",
        "read time": 12
    }
]